cherry_ua/__init__.py
cherry_ua/assertions.py
cherry_ua/cherry.py
cherry_ua/constants.py
cherry_ua/decorators.py
cherry_ua/exceptions.py
cherry_ua/network.py
cherry_ua/utils.py
cherry_ua/validator.py
cherry_ua_staging-0.0.8.dist-info/LICENSE
cherry_ua_staging-0.0.8.dist-info/METADATA
cherry_ua_staging-0.0.8.dist-info/WHEEL
cherry_ua_staging-0.0.8.dist-info/top_level.txt
cherry_ua_staging-0.0.8.dist-info/RECORD
