Metadata-Version: 2.1
Name: cherry-ua-staging
Version: 0.0.8
Summary: A library to generate random user-agent
Home-page: https://github.com/abhishek72850/cherry-ua/
Author: Abhishek Kumar
Author-email: abhishekk728@yahoo.com
License: UNKNOWN
Project-URL: Bug Tracker, https://github.com/abhishek72850/cherry-ua/issues
Platform: UNKNOWN
Classifier: Programming Language :: Python :: 3
Classifier: License :: OSI Approved :: MIT License
Classifier: Operating System :: OS Independent
Requires-Python: >=3.8
License-File: LICENSE
